browsernative/__init__.py
browsernative/client.py
browsernative-1.0.0.dist-info/licenses/LICENSE
browsernative-1.0.0.dist-info/METADATA
browsernative-1.0.0.dist-info/WHEEL
browsernative-1.0.0.dist-info/top_level.txt
browsernative-1.0.0.dist-info/RECORD
