Metadata-Version: 2.4
Name: browsernative
Version: 1.0.0
Summary: Lightning-fast web scraping Python SDK - 11x faster than traditional scrapers
Home-page: https://github.com/monostate/browsernative-python
Author: BNCA Team
Author-email: BNCA Team <support@monostate.ai>
License: MIT
Project-URL: Homepage, https://bnca.monostate.ai
Project-URL: Documentation, https://docs.bnca.dev
Project-URL: Repository, https://github.com/monostate/browsernative-python
Project-URL: Issues, https://github.com/monostate/browsernative-python/issues
Keywords: web scraping,browser automation,ai analysis,screenshot,pdf parsing,data extraction,web crawler,html parser,content extraction
Classifier: Development Status :: 5 - Production/Stable
Classifier: Intended Audience :: Developers
Classifier: Topic :: Software Development :: Libraries :: Python Modules
Classifier: Topic :: Internet :: WWW/HTTP :: Dynamic Content
Classifier: Topic :: Text Processing :: Markup :: HTML
Classifier: License :: OSI Approved :: MIT License
Classifier: Programming Language :: Python :: 3
Classifier: Programming Language :: Python :: 3.7
Classifier: Programming Language :: Python :: 3.8
Classifier: Programming Language :: Python :: 3.9
Classifier: Programming Language :: Python :: 3.10
Classifier: Programming Language :: Python :: 3.11
Classifier: Programming Language :: Python :: 3.12
Classifier: Operating System :: OS Independent
Requires-Python: >=3.7
License-File: LICENSE
Requires-Dist: requests>=2.25.0
Provides-Extra: dev
Requires-Dist: pytest>=6.0; extra == "dev"
Requires-Dist: pytest-cov>=2.0; extra == "dev"
Requires-Dist: black>=21.0; extra == "dev"
Requires-Dist: flake8>=3.8; extra == "dev"
Requires-Dist: mypy>=0.900; extra == "dev"
Requires-Dist: twine>=3.0; extra == "dev"
Dynamic: author
Dynamic: home-page
Dynamic: license-file
Dynamic: requires-python
